{
    "key": "group_5e2ed4684dc33",
    "title": "CPT Job",
    "fields": [
        {
            "key": "field_5e2ed46f4d1a3",
            "label": "Recruiter",
            "name": "job_recruiter",
            "type": "post_object",
            "instructions": "",
            "required": 0,
            "conditional_logic": 0,
            "wrapper": {
                "width": "",
                "class": "",
                "id": ""
            },
            "post_type": [
                "recruiter"
            ],
            "taxonomy": "",
            "allow_null": 0,
            "multiple": 0,
            "return_format": "object",
            "ui": 1
        }
    ],
    "location": [
        [
            {
                "param": "post_type",
                "operator": "==",
                "value": "job_offer"
            }
        ]
    ],
    "menu_order": 0,
    "position": "normal",
    "style": "default",
    "label_placement": "top",
    "instruction_placement": "label",
    "hide_on_screen": "",
    "active": 1,
    "description": "",
    "modified": 1580127432
}